CHANGELOG.rst
LICENSE.txt
MANIFEST.in
README.rst
TODO.rst
VERSION.txt
setup.cfg
setup.py
lessc/__init__.py
lessc/compiler.py
lessc/test.py
lessc.egg-info/PKG-INFO
lessc.egg-info/SOURCES.txt
lessc.egg-info/dependency_links.txt
lessc.egg-info/requires.txt
lessc.egg-info/top_level.txt
lessc.egg-info/zip-safe
lessc/res/test-01.css
lessc/res/test-01.less
lessc/res/test-02-colors.less
lessc/res/test-02.css
lessc/res/test-02.less
lessc/res/test-03.css
lessc/res/test-03.less