Metadata-Version: 1.1
Name: lessc
Version: 0.1.2
Summary: A Python less compiler
Home-page: http://github.com/canaryhealth/lessc
Author: Philip J Grabner, Canary Health Inc
Author-email: oss@canary.md
License: MIT (http://opensource.org/licenses/MIT)
Keywords: less css compiler
Platform: UNKNOWN
Classifier: Development Status :: 3 - Alpha
Classifier: Environment :: Console
Classifier: Intended Audience :: Developers
Classifier: Programming Language :: Python
Classifier: Operating System :: OS Independent
Classifier: Topic :: Internet
Classifier: Topic :: Software Development
Classifier: Topic :: Internet :: WWW/HTTP
Classifier: Natural Language :: English
Classifier: License :: OSI Approved :: MIT License
Classifier: License :: Public Domain
